rude/__init__.py
rude-0.1a1.dist-info/METADATA
rude-0.1a1.dist-info/WHEEL
rude-0.1a1.dist-info/top_level.txt
rude-0.1a1.dist-info/RECORD
